LICENSE
README.rst
setup.py
grecx/__init__.py
grecx/config.py
grecx.egg-info/PKG-INFO
grecx.egg-info/SOURCES.txt
grecx.egg-info/dependency_links.txt
grecx.egg-info/requires.txt
grecx.egg-info/top_level.txt
grecx/datasets/__init__.py
grecx/datasets/diff_net_dataset.py
grecx/datasets/light_gcn_dataset.py
grecx/evaluation/__init__.py
grecx/evaluation/ranking.py
grecx/layers/__init__.py
grecx/layers/embedding.py
grecx/layers/light_gcn.py
grecx/layers/ngcf.py
grecx/layers/user_item_embedding.py
grecx/metrics/__init__.py
grecx/metrics/libranking.dll
grecx/metrics/libranking.so
grecx/metrics/ranking.py
grecx/utils/__init__.py
grecx/utils/data_utils.py
grecx/vector_search/__init__.py
grecx/vector_search/vector_search.py